gaitmap_mad/__init__.py
gaitmap_mad/event_detection/__init__.py
gaitmap_mad/event_detection/_filtered_rampp_event_detection.py
gaitmap_mad/event_detection/_rampp_event_detection.py
gaitmap_mad/gait_detection/__init__.py
gaitmap_mad/gait_detection/_ullrich_gait_sequence_detection.py
gaitmap_mad/preprocessing/__init__.py
gaitmap_mad/preprocessing/sensor_alignment/__init__.py
gaitmap_mad/preprocessing/sensor_alignment/_forward_direction_alignment.py
gaitmap_mad/stride_segmentation/__init__.py
gaitmap_mad/stride_segmentation/dtw/__init__.py
gaitmap_mad/stride_segmentation/dtw/_barth_dtw.py
gaitmap_mad/stride_segmentation/dtw/_base_dtw.py
gaitmap_mad/stride_segmentation/dtw/_constrained_barth_dtw.py
gaitmap_mad/stride_segmentation/dtw/_dtw_templates/__init__.py
gaitmap_mad/stride_segmentation/dtw/_dtw_templates/barth_original_template.csv
gaitmap_mad/stride_segmentation/dtw/_dtw_templates/templates.py
gaitmap_mad/stride_segmentation/dtw/_vendored_tslearn.py
gaitmap_mad/stride_segmentation/hmm/__init__.py
gaitmap_mad/stride_segmentation/hmm/_hmm_feature_transform.py
gaitmap_mad/stride_segmentation/hmm/_hmm_stride_segmentation.py
gaitmap_mad/stride_segmentation/hmm/_pre_trained_models/__init__.py
gaitmap_mad/stride_segmentation/hmm/_pre_trained_models/fallriskpd_at_lab_model.json
gaitmap_mad/stride_segmentation/hmm/_segmentation_model.py
gaitmap_mad/stride_segmentation/hmm/_simple_model.py
gaitmap_mad/stride_segmentation/hmm/_utils.py
gaitmap_mad/trajectory_reconstruction/__init__.py
gaitmap_mad/trajectory_reconstruction/position_methods/__init__.py
gaitmap_mad/trajectory_reconstruction/position_methods/_piece_wise_linear_dedrifted_integration.py
gaitmap_mad-2.5.2.dist-info/LICENSE
gaitmap_mad-2.5.2.dist-info/METADATA
gaitmap_mad-2.5.2.dist-info/WHEEL
gaitmap_mad-2.5.2.dist-info/RECORD
