Metadata-Version: 2.3
Name: gaitmap_mad
Version: 2.5.2
Summary: Specific algorithm implementaions by the mad_lab
License: AGPL-3.0
Author: Arne Küderle
Author-email: arne.kuederle@fau.de
Requires-Python: >=3.8,<4.0
Classifier: License :: OSI Approved :: GNU Affero General Public License v3
Classifier: Programming Language :: Python :: 3
Classifier: Programming Language :: Python :: 3.8
Classifier: Programming Language :: Python :: 3.9
Classifier: Programming Language :: Python :: 3.10
Classifier: Programming Language :: Python :: 3.11
Classifier: Programming Language :: Python :: 3.12
Classifier: Programming Language :: Python :: 3.13
Project-URL: Homepage, https://github.com/mad-lab-fau/gaitmap
Project-URL: Repository, https://github.com/mad-lab-fau/gaitmap
